memgraph/__init__.py
memgraph-0.0.1.dist-info/LICENSE
memgraph-0.0.1.dist-info/METADATA
memgraph-0.0.1.dist-info/WHEEL
memgraph-0.0.1.dist-info/top_level.txt
memgraph-0.0.1.dist-info/RECORD
