Metadata-Version: 2.1
Name: memgraph
Version: 0.0.1
Summary: In memory graph database
Home-page: https://github.com/mfayoumi/memgraph
Author: Mahmoud Alfayoumi
Author-email: mfayoumi.dev@gmail.com
License: UNKNOWN
Platform: UNKNOWN
Classifier: Programming Language :: Python :: 3
Classifier: License :: OSI Approved :: MIT License
Classifier: Operating System :: OS Independent
Requires-Python: >=3.6
